AUTHORS
CHANGES.rst
LICENSE
MANIFEST.in
README.rst
TODO.md
setup.py
docs/.gitignore
docs/Makefile
docs/api-actuator-dynamixel_ax12.rst
docs/api-computer_vision-circle_detection.rst
docs/api-controller-rule_based_controller.rst
docs/api.rst
docs/conf.py
docs/developer.rst
docs/index.rst
docs/install_opencv3_from_git.rst
docs/intro.rst
docs/make.bat
opencv_tests_and_calibration_scripts/hough_circle_transform_calibration.py
scripts/vor12gui
vor12/__init__.py
vor12.egg-info/PKG-INFO
vor12.egg-info/SOURCES.txt
vor12.egg-info/dependency_links.txt
vor12.egg-info/requires.txt
vor12.egg-info/top_level.txt
vor12/actuator/__init__.py
vor12/actuator/dynamixel_ax12.py
vor12/actuator/fake.py
vor12/computer_vision/__init__.py
vor12/computer_vision/circle_detection.py
vor12/controller/__init__.py
vor12/controller/rule_based_controller.py