Metadata-Version: 1.1
Name: vor12
Version: 0.2.dev21
Summary: The Vor12 project, a mobile video camera created for object tracking experiments.
Home-page: http://www.jdhp.org/
Author: Jeremie DECOCK
Author-email: jd.jdhp@gmail.com
License: UNKNOWN
Download-URL: http://www.jdhp.org/
Keywords: opencv image recognition dynamixel ax12 ax-12 servo actuator robotics
Platform: UNKNOWN
Classifier: Development Status :: 4 - Beta
Classifier: Intended Audience :: Education
Classifier: Intended Audience :: End Users/Desktop
Classifier: Intended Audience :: Science/Research
Classifier: License :: OSI Approved :: MIT License
Classifier: Natural Language :: English
Classifier: Operating System :: OS Independent
Classifier: Programming Language :: Python :: 3.4
Classifier: Topic :: Multimedia :: Video
Classifier: Topic :: Multimedia :: Video :: Capture
Classifier: Topic :: Scientific/Engineering :: Image Recognition
Classifier: Topic :: Scientific/Engineering :: Artificial Intelligence
